{"talks":{"ar":{"talk":"ar","track":"misc101","speakers":["David Chang"],"begin":"2018-08-11T15:20:00+08:00","end":"2018-08-11T16:00:00+08:00","title":"結合 AR 與人臉辨識之開源戰鬥力探測器 ","intro":"是的，就是七龍珠中的戰鬥力探測器。我們做了一款辨識工程師們開源貢獻力的的戰鬥力探測器，可以透過人臉來探測身邊的開源大大。本次分享分為幾個部分：\n1. 人臉辨識技術\n2. 前端 Augmented Reality 即時顯示\n3. 消夜垃圾話中誕生的 side project，從無到有的過程與收穫分享 ","addition":"* Language: 漢語 / Mandarin Chinese\n* Audience: 任何覺得標題有趣的人\n* Difficulty: Begineer / 入門"}},"tracks":{"misc101":{"group":"misc","track":"misc101","communities":["coscup"],"room":"IB101"}},"speakers":{"David Chang":{"speaker":"David Chang","name":"David Chang","intro":"後端工程師 / DevOps，喜歡編寫 bash script 自動化維運過程中的大小事。剛開始投入 Kubernetes 的源碼貢獻與國內社群活動，以及 Kubernetes 相關演討會演講。","link":"","avatar":null}},"communities":{"coscup":{"community":"coscup","link":"https://coscup.org","image":null}}}