{"talks":{"education-bof":{"talk":"education-bof","track":"bofday2","speakers":["Staff"],"begin":"2018-08-12T12:30:00+08:00","end":"2018-08-12T13:30:00+08:00","title":"開源與教育 BoF ","intro":"(發起: BobChao)\n\n這次的 COSCUP 講題有不少跟開源 / 教育相關，想邀請關心相關議題的人來聚首，大家聊聊認識一下。由於約在中午時間，有興趣參與的人請帶點吃的來邊吃邊聊。內容大概會是彼此認識，介紹自己參與的教育相關事務，然後就大亂鬥（？）\n\n欲出席者請到 [BoF 文件] (https://docs.google.com/document/d/14I51R_FauCe9kwhz3vd1EQhnlNS6ALh9OksNtc3aH9Y/edit#heading=h.qd580qehe6es) 登記自己的名字\n\n----\n[Collaborative notes on HackMD](https://hackmd.io/c/coscup18-misc/%2Fcoscup18-misc307-education-bof)","addition":"","language":"","difficulty":"","audience":""}},"tracks":{"bofday2":{"group":"bofday2","track":"bofday2","communities":["coscup"],"room":"IB307","title":"BoF"}},"speakers":{"Staff":{"speaker":"Staff","name":"Staff","intro":"COSCUP x GNOME.Asia x openSUSE.Asia Staff","link":"","avatar":"/assets/coscup-1A2gYj9iSEiiUXRUuW2quhoIP7LFgJvmh.png"}},"communities":{"coscup":{"community":"coscup","title":"COSCUP","intro":"COSCUP is an annual conference held by Taiwanese Open source community participants since 2006. It's a major force of Free software movement advocacy in Taiwan. The event is often held with talks, sponsor and communities booths, and Birds of a feather. In addition to international speakers, many Taiwanese local Open Source contributors often give their talks here.\n\nThe chief organizer, staffs, and speakers are all volunteers.","link":"https://coscup.org","image":null}}}